setup.py
devdoo/__init__.py
devdoo/broker.py
devdoo/brokers.py
devdoo/check.py
devdoo/console.py
devdoo/convert.py
devdoo/data_response.py
devdoo/database_delete.py
devdoo/database_get.py
devdoo/database_mongo.py
devdoo/database_post.py
devdoo/database_prepare.py
devdoo/database_put.py
devdoo/database_service.py
devdoo/devdoo_broker.py
devdoo/devdoo_database.py
devdoo/pack.py
devdoo/service.py
devdoo/services.py
devdoo/socket.py
devdoo/stack.py
devdoo/stacks.py
devdoo/status.py
devdoo/validate.py
devdoo/yml.py
devdoo/yaml/__init__.py
devdoo/yaml/composer.py
devdoo/yaml/constructor.py
devdoo/yaml/cyaml.py
devdoo/yaml/dumper.py
devdoo/yaml/emitter.py
devdoo/yaml/error.py
devdoo/yaml/events.py
devdoo/yaml/loader.py
devdoo/yaml/nodes.py
devdoo/yaml/parser.py
devdoo/yaml/reader.py
devdoo/yaml/representer.py
devdoo/yaml/resolver.py
devdoo/yaml/scanner.py
devdoo/yaml/serializer.py
devdoo/yaml/tokens.py
devdoo/yaml/__init__.py
devdoo/yaml/composer.py
devdoo/yaml/constructor.py
devdoo/yaml/cyaml.py
devdoo/yaml/dumper.py
devdoo/yaml/emitter.py
devdoo/yaml/error.py
devdoo/yaml/events.py
devdoo/yaml/loader.py
devdoo/yaml/nodes.py
devdoo/yaml/parser.py
devdoo/yaml/reader.py
devdoo/yaml/representer.py
devdoo/yaml/resolver.py
devdoo/yaml/scanner.py
devdoo/yaml/serializer.py
devdoo/yaml/tokens.py
packagetest117.egg-info/PKG-INFO
packagetest117.egg-info/SOURCES.txt
packagetest117.egg-info/dependency_links.txt
packagetest117.egg-info/not-zip-safe
packagetest117.egg-info/top_level.txt